geosnap/__init__.py
geosnap/_data.py
geosnap/analyze/__init__.py
geosnap/analyze/_cluster_wrappers.py
geosnap/analyze/_model_results.py
geosnap/analyze/_region_wrappers.py
geosnap/analyze/dynamics.py
geosnap/analyze/geodemo.py
geosnap/analyze/incs.py
geosnap/analyze/network.py
geosnap/analyze/segdyn.py
geosnap/harmonize/__init__.py
geosnap/harmonize/harmonize.py
geosnap/io/__init__.py
geosnap/io/bea_regions.csv
geosnap/io/constructors.py
geosnap/io/ejscreen_codebook.csv
geosnap/io/gadm.py
geosnap/io/inflation.csv
geosnap/io/lodes.csv
geosnap/io/metadata.md
geosnap/io/msa_definitions.csv
geosnap/io/networkio.py
geosnap/io/nlcd_definitions.csv
geosnap/io/stfipstable.csv
geosnap/io/storage.py
geosnap/io/util.py
geosnap/io/variables.csv
geosnap/tests/README.md
geosnap/tests/_dl_data.py
geosnap/tests/get_data.py
geosnap/tests/test_add_data.py
geosnap/tests/test_clusters.py
geosnap/tests/test_constructors.py
geosnap/tests/test_data_boundaries.py
geosnap/tests/test_datastore.py
geosnap/tests/test_diagnostics.py
geosnap/tests/test_dynamics.py
geosnap/tests/test_forward_sim.py
geosnap/tests/test_get_gadm.py
geosnap/tests/test_harmonize.py
geosnap/tests/test_incs.py
geosnap/tests/test_isochrones.py
geosnap/tests/test_plots.py
geosnap/tests/test_segdyn.py
geosnap/tests/baseline_images/san_diego_kmeans.png
geosnap/util/__init__.py
geosnap/util/util.py
geosnap/visualize/__init__.py
geosnap/visualize/descriptives.py
geosnap/visualize/mapping.py
geosnap/visualize/seq.py
geosnap/visualize/skplt.py
geosnap/visualize/transitions.py
geosnap-0.15.3.dist-info/licenses/LICENSE.txt
geosnap-0.15.3.dist-info/METADATA
geosnap-0.15.3.dist-info/WHEEL
geosnap-0.15.3.dist-info/top_level.txt
geosnap-0.15.3.dist-info/RECORD
