Metadata-Version: 2.4
Name: geosnap
Version: 0.15.3
Summary: The Geospatial Neighborhood Analysis Package
Author-email: Eli Knaap <ek@knaaptime.com>, Serge Rey <sjsrey@gmail.com>
Maintainer: geosnap contributors
License: BSD 3-Clause
Project-URL: Home, https://github.com/oturns/geosnap/
Project-URL: Repository, https://github.com/oturns/geosnap
Keywords: geodemographics, neighborhood dynamics, urban data science, spatial analysis
Classifier: Programming Language :: Python :: 3
Classifier: License :: OSI Approved :: BSD License
Classifier: Operating System :: OS Independent
Classifier: Intended Audience :: Science/Research
Classifier: Topic :: Scientific/Engineering :: GIS
Requires-Python: >=3.8
License-File: LICENSE.txt
Requires-Dist: numpy
Requires-Dist: pandas
Requires-Dist: geopandas>=0.9
Requires-Dist: matplotlib
Requires-Dist: scikit-learn
Requires-Dist: seaborn
Requires-Dist: libpysal
Requires-Dist: mapclassify
Requires-Dist: giddy>=2.2.1
Requires-Dist: xlrd
Requires-Dist: platformdirs
Requires-Dist: tqdm
Requires-Dist: quilt3>=3.6
Requires-Dist: pyarrow>=0.14.1
Requires-Dist: contextily
Requires-Dist: tobler>=0.8.2
Requires-Dist: spopt>=0.3.0
Requires-Dist: fsspec
Requires-Dist: s3fs
Requires-Dist: segregation>=2.1
Requires-Dist: pyproj>=3
Requires-Dist: pandana
Requires-Dist: pooch
Provides-Extra: dev
Requires-Dist: pre-commit; extra == "dev"
Provides-Extra: docs
Requires-Dist: nbsphinx; extra == "docs"
Requires-Dist: numpydoc; extra == "docs"
Requires-Dist: pandoc; extra == "docs"
Requires-Dist: sphinx; extra == "docs"
Requires-Dist: sphinxcontrib-bibtex; extra == "docs"
Requires-Dist: sphinx_bootstrap_theme; extra == "docs"
Requires-Dist: mkdocs-jupyter; extra == "docs"
Requires-Dist: myst-parser; extra == "docs"
Provides-Extra: tests
Requires-Dist: codecov; extra == "tests"
Requires-Dist: coverage; extra == "tests"
Requires-Dist: pytest; extra == "tests"
Requires-Dist: pytest-mpl; extra == "tests"
Requires-Dist: pytest-cov; extra == "tests"
Requires-Dist: matplotlib; extra == "tests"
Requires-Dist: matplotlib-scalebar; extra == "tests"
Requires-Dist: watermark; extra == "tests"
Requires-Dist: pygraphviz; extra == "tests"
Requires-Dist: hdbscan; extra == "tests"
Requires-Dist: osmnx; extra == "tests"
Dynamic: license-file
